similtext.py
similtext-0.9.0.dist-info/licenses/LICENSE
similtext-0.9.0.dist-info/METADATA
similtext-0.9.0.dist-info/WHEEL
similtext-0.9.0.dist-info/top_level.txt
similtext-0.9.0.dist-info/RECORD
